arithmeticskill/Snipsspec
arithmeticskill/__init__.py
arithmeticskill/arithmeticskill.py
snips_skill_maths-0.0.2.dist-info/DESCRIPTION.rst
snips_skill_maths-0.0.2.dist-info/METADATA
snips_skill_maths-0.0.2.dist-info/RECORD
snips_skill_maths-0.0.2.dist-info/WHEEL
snips_skill_maths-0.0.2.dist-info/metadata.json
snips_skill_maths-0.0.2.dist-info/top_level.txt
