Metadata-Version: 2.0
Name: snips-skill-maths
Version: 0.0.2
Summary: answer maths questions
Home-page: UNKNOWN
Author: steve ryan
Author-email: stever@syntithenai.com
License: MIT
Keywords: snips
Platform: UNKNOWN
